demo/__init__.py
demo/func.py
deptest1_zs-0.0.1.dist-info/METADATA
deptest1_zs-0.0.1.dist-info/WHEEL
deptest1_zs-0.0.1.dist-info/top_level.txt
deptest1_zs-0.0.1.dist-info/RECORD
